{
  "type":"FeatureCollection",
  "crs": {
    "type":"name",
    "properties": {
      "name": "urn:ogc:def:crs:OGC:1.3:CRS84"
    }
  }
  ,
  "features":[ {
    "type":"Feature",
    "properties": {
      "OBJECTID": 812, "Name": "Selkirk Provincial Park", "Type": "Provincial Park", "Website": "https://www.ontarioparks.com/park/selkirk", "created_us": "MDAVIS", "created_da": "2016/03/31", "last_edite": "MDAVIS", "last_edi_1": "2016/03/31", "PhoneNum": null
    }
    ,
    "geometry": {
      "type": "Point", "coordinates": [-79.95847781935836, 42.81290140743731]
    }
  }
  ,
  {
    "type":"Feature",
    "properties": {
      "OBJECTID": 813, "Name": "James N. Allan Provincial Park", "Type": "Provincial Park", "Website": "https://www.ontarioparks.com/park/jamesnallan", "created_us": "MDAVIS", "created_da": "2016/03/31", "last_edite": "MDAVIS", "last_edi_1": "2016/03/31", "PhoneNum": null
    }
    ,
    "geometry": {
      "type": "Point", "coordinates": [-79.65662222096724, 42.84823483605928]
    }
  }
  ,
  {
    "type":"Feature",
    "properties": {
      "OBJECTID": 814, "Name": "Rock Point Provincial Park", "Type": "Provincial Park", "Website": "https://www.ontarioparks.com/park/rockpoint", "created_us": "MDAVIS", "created_da": "2016/03/31", "last_edite": "MDAVIS", "last_edi_1": "2016/03/31", "PhoneNum": null
    }
    ,
    "geometry": {
      "type": "Point", "coordinates": [-79.5547834053947, 42.852561140792055]
    }
  }
  ]
}
